uniswapx_sdk/__init__.py
uniswapx_sdk/api.py
uniswapx_sdk/constants.py
uniswapx_sdk/decoder.py
uniswapx_sdk/encoder.py
uniswapx_sdk/exceptions.py
uniswapx_sdk/resolver.py
uniswapx_sdk-0.0.2.dist-info/LICENSE
uniswapx_sdk-0.0.2.dist-info/METADATA
uniswapx_sdk-0.0.2.dist-info/WHEEL
uniswapx_sdk-0.0.2.dist-info/top_level.txt
uniswapx_sdk-0.0.2.dist-info/RECORD
